mkdocs_material_adr/__init__.py
mkdocs_material_adr/base_adr.html
mkdocs_material_adr/main.html
mkdocs_material_adr/mkdocs_theme.yml
mkdocs_material_adr/partials/adr.html
mkdocs_material_adr/partials/content.html
mkdocs_material_adr/plugins/graph/__init__.py
mkdocs_material_adr/plugins/graph/plugin.py
mkdocs_material_adr/stylesheets/adr.css
mkdocs_material_adr-1.2.1.dist-info/entry_points.txt
mkdocs_material_adr-1.2.1.dist-info/LICENSE
mkdocs_material_adr-1.2.1.dist-info/WHEEL
mkdocs_material_adr-1.2.1.dist-info/METADATA
mkdocs_material_adr-1.2.1.dist-info/RECORD
