Metadata-Version: 2.1
Name: mkdocs-material-adr
Version: 1.2.1
Summary: 
Home-page: https://github.com/Kl0ven/mkdocs-material-adr
License: Apache-2.0
Author: jeanloup.monnier
Author-email: jean-loup.monnier@spikeelabs.fr
Requires-Python: >=3.9,<4.0
Classifier: License :: OSI Approved :: Apache Software License
Classifier: Programming Language :: Python :: 3
Classifier: Programming Language :: Python :: 3.9
Classifier: Programming Language :: Python :: 3.10
Classifier: Programming Language :: Python :: 3.11
Requires-Dist: pydantic (>=2.4.0,<3.0.0)
Project-URL: Repository, https://github.com/Kl0ven/mkdocs-material-adr
